sliceoptim/__init__.py
sliceoptim/core.py
sliceoptim/io.py
sliceoptim/samples.py
sliceoptim/data/implemented_params.yml
sliceoptim/data/slic3r_help_file.txt
sliceoptim-0.1.2.dist-info/AUTHORS.md
sliceoptim-0.1.2.dist-info/LICENSE
sliceoptim-0.1.2.dist-info/METADATA
sliceoptim-0.1.2.dist-info/WHEEL
sliceoptim-0.1.2.dist-info/top_level.txt
sliceoptim-0.1.2.dist-info/RECORD
