Metadata-Version: 2.1
Name: sliceoptim
Version: 0.1.2
Summary: Python package providing tools to optimize slicer settings for FDM 3D printers.
Home-page: https://github.com/oiesauvage/sliceoptim
Author: Nils Artiges
License: apache 2.0
Project-URL: Documentation, https://oiesauvage.github.io/sliceoptim/index.html
Platform: any
Classifier: Development Status :: 4 - Beta
Classifier: Programming Language :: Python
Requires-Python: >=3.7
License-File: LICENSE
License-File: AUTHORS.md
Requires-Dist: numpy (>=1.21)
Requires-Dist: scikit-optimize (>=0.8)
Requires-Dist: pandas (>=1.3)
Requires-Dist: tinydb (>=4.4)
Requires-Dist: importlib-metadata ; python_version >= "3.7"
Provides-Extra: docs
Requires-Dist: sphinx (>=4.1) ; extra == 'docs'
Requires-Dist: sphinx-rtd-theme (>=0.5) ; extra == 'docs'
Requires-Dist: m2r2 (>=0.3) ; extra == 'docs'
Provides-Extra: testing
Requires-Dist: pytest ; extra == 'testing'
Requires-Dist: pytest-cov ; extra == 'testing'
